arbor/__init__.py
arbor/__main__.py
arbor/cli.py
arbor/client.py
arbor/core/__init__.py
arbor/core/config.py
arbor/core/logging.py
arbor/integrations/__init__.py
arbor/integrations/dspy/__init__.py
arbor/integrations/dspy/arbor_provider.py
arbor/integrations/dspy/grpo_optimizer.py
arbor/server/__init__.py
arbor/server/main.py
arbor/server/api/__init__.py
arbor/server/api/schemas.py
arbor/server/api/routes/__init__.py
arbor/server/api/routes/files.py
arbor/server/api/routes/grpo.py
arbor/server/api/routes/inference.py
arbor/server/services/__init__.py
arbor/server/services/dependencies.py
arbor/server/services/comms/__init__.py
arbor/server/services/comms/async_batch_requester.py
arbor/server/services/comms/async_dataloader_wrapper.py
arbor/server/services/comms/control_client.py
arbor/server/services/comms/control_server.py
arbor/server/services/inference/__init__.py
arbor/server/services/inference/vllm_client.py
arbor/server/services/inference/vllm_serve.py
arbor/server/services/jobs/__init__.py
arbor/server/services/jobs/file_train_job.py
arbor/server/services/jobs/grpo_job.py
arbor/server/services/jobs/inference_job.py
arbor/server/services/jobs/inference_launch_config.py
arbor/server/services/jobs/job.py
arbor/server/services/managers/base_manager.py
arbor/server/services/managers/file_manager.py
arbor/server/services/managers/file_train_manager.py
arbor/server/services/managers/gpu_manager.py
arbor/server/services/managers/grpo_manager.py
arbor/server/services/managers/inference_manager.py
arbor/server/services/managers/job_manager.py
arbor/training/__init__.py
arbor/training/dpo/__init__.py
arbor/training/dpo/trainer.py
arbor/training/grpo/__init__.py
arbor/training/grpo/config.py
arbor/training/grpo/trainer.py
arbor/training/sft/__init__.py
arbor/training/sft/trainer.py
arbor/training/utils/__init__.py
arbor/training/utils/arg_parser.py
arbor/utils/__init__.py
arbor/utils/format_detection.py
arbor/utils/helpers.py
arbor/utils/process_runner.py
arbor_ai-0.2.17.dist-info/licenses/LICENSE
arbor_ai-0.2.17.dist-info/METADATA
arbor_ai-0.2.17.dist-info/WHEEL
arbor_ai-0.2.17.dist-info/entry_points.txt
arbor_ai-0.2.17.dist-info/top_level.txt
arbor_ai-0.2.17.dist-info/RECORD
