Metadata-Version: 2.4
Name: arbor-ai
Version: 0.2.17
Summary: A framework for optimizing DSPy programs
Author-email: Noah Ziems <nziems2@nd.edu>
Project-URL: Homepage, https://github.com/Ziems/arbor
Project-URL: Issues, https://github.com/Ziems/arbor/issues
Requires-Python: <3.14,>=3.11
License-File: LICENSE
Requires-Dist: torch>=2.7.0
Requires-Dist: fastapi
Requires-Dist: uvicorn
Requires-Dist: click
Requires-Dist: pydantic-settings
Requires-Dist: dspy
Requires-Dist: vllm==0.10.0
Requires-Dist: transformers
Requires-Dist: trl==0.23.1
Requires-Dist: peft
Requires-Dist: setuptools<79.0.1,>=76.0.0
Requires-Dist: pyzmq>=26.4.0
Requires-Dist: pyyaml>=6.0.2
Requires-Dist: wandb
Requires-Dist: httpx
Requires-Dist: coolname
Requires-Dist: nvidia-ml-py
Requires-Dist: textual
Requires-Dist: deepspeed>=0.17.6
Dynamic: license-file
